mujoco_logger/__init__.py
mujoco_logger/convention.py
mujoco_logger/emulator.py
mujoco_logger/logger.py
mujoco_logger/sim_log.py
mujoco_logger-0.1.2.dist-info/LICENSE
mujoco_logger-0.1.2.dist-info/METADATA
mujoco_logger-0.1.2.dist-info/WHEEL
mujoco_logger-0.1.2.dist-info/RECORD
