Metadata-Version: 2.1
Name: mujoco-logger
Version: 0.1.2
Summary: Handy tool to log simulation from MuJoCo
License: GNU General Public License v3.0
Author: Lev Kozlov
Author-email: kozlov.l.a10@gmail.com
Requires-Python: >=3.10,<4.0
Classifier: License :: Other/Proprietary License
Classifier: Programming Language :: Python :: 3
Classifier: Programming Language :: Python :: 3.10
Classifier: Programming Language :: Python :: 3.11
Classifier: Programming Language :: Python :: 3.12
Provides-Extra: examples
Requires-Dist: mujoco (>=3.1.1,<4.0.0)
Requires-Dist: numpy-quaternion (>=2023.0.2,<2024.0.0)
